mcp_server_weather_lei/__init__.py
mcp_server_weather_lei/tool.py
mcp_server_weather_lei-0.1.5.dist-info/METADATA
mcp_server_weather_lei-0.1.5.dist-info/WHEEL
mcp_server_weather_lei-0.1.5.dist-info/entry_points.txt
mcp_server_weather_lei-0.1.5.dist-info/top_level.txt
mcp_server_weather_lei-0.1.5.dist-info/RECORD
